deepomatic_api-0.10.0-py3.8-nspkg.pth
deepomatic/api/__init__.py
deepomatic/api/client.py
deepomatic/api/exceptions.py
deepomatic/api/http_helper.py
deepomatic/api/http_retry.py
deepomatic/api/inference.py
deepomatic/api/inputs.py
deepomatic/api/mixins.py
deepomatic/api/resource.py
deepomatic/api/utils.py
deepomatic/api/version.py
deepomatic/api/resources/__init__.py
deepomatic/api/resources/account.py
deepomatic/api/resources/network.py
deepomatic/api/resources/recognition.py
deepomatic/api/resources/task.py
deepomatic_api-0.10.0.data/data/requirements.txt
deepomatic_api-0.10.0.dist-info/LICENSE
deepomatic_api-0.10.0.dist-info/METADATA
deepomatic_api-0.10.0.dist-info/WHEEL
deepomatic_api-0.10.0.dist-info/namespace_packages.txt
deepomatic_api-0.10.0.dist-info/top_level.txt
deepomatic_api-0.10.0.dist-info/RECORD
