Metadata-Version: 2.1
Name: deepomatic-api
Version: 0.10.0
Summary: Deepomatic API client
Home-page: https://github.com/deepomatic/deepomatic-client-python
Author: deepomatic
Author-email: support@deepomatic.com
License: MIT License
Project-URL: Product, https://www.deepomatic.com
Project-URL: Documentation, https://docs.deepomatic.com/deepomatic-api-v0-7
Project-URL: Source, https://github.com/deepomatic/deepomatic-client-python
Project-URL: Tracker, https://github.com/deepomatic/deepomatic-client-python/issues
Platform: UNKNOWN
Classifier: Operating System :: OS Independent
Classifier: Programming Language :: Python
Classifier: Programming Language :: Python :: 3
Classifier: Programming Language :: Python :: 3.8
Classifier: Programming Language :: Python :: 3.9
Classifier: Programming Language :: Python :: 3.10
Classifier: Programming Language :: Python :: 3.11
Requires-Python: >=3.8
License-File: LICENSE
Requires-Dist: numpy<2,>=1.10.0
Requires-Dist: six<2,>=1.10.0
Requires-Dist: requests<3,>=2.19.0
Requires-Dist: tenacity<9,>=5.1
